__init__.py
controll.py
catalog/__init__.py
datacheck/__init__.py
datasource/__init__.py
ingestion/__init__.py
ingestion/command_interface.py
ingestion/meta_interface.py
orm/__init__.py
orm/meta_db.py
orm/meta_model.py
orm/meta_session.py
pipeline/__init__.py
server/__init__.py
server/command_interface.py
server/meta_interface.py
src/catalog/__init__.py
src/datacheck/__init__.py
src/datasource/__init__.py
src/ingestion/__init__.py
src/ingestion/command_interface.py
src/ingestion/meta_interface.py
src/orm/__init__.py
src/orm/meta_db.py
src/orm/meta_model.py
src/orm/meta_session.py
src/pipeline/__init__.py
src/server/__init__.py
src/server/command_interface.py
src/server/meta_interface.py
src/util/__init__.py
src/util/logger.py
src/util/util.py
util/__init__.py
util/logger.py
util/util.py
z_test/AES_01.py
z_test/__init__.py
z_test/cron_parsing.py
z_test/util.py
z_test/util_test.py
shaidata-0.11.dist-info/METADATA
shaidata-0.11.dist-info/WHEEL
shaidata-0.11.dist-info/top_level.txt
shaidata-0.11.dist-info/RECORD
