Metadata-Version: 2.1
Name: shaidata
Version: 0.11
Summary: Shinhan AI Data Pipeline
Author: Shinhan AI
Requires-Python: >=3.9.13
Requires-Dist: bcrypt (==4.0.1)
Requires-Dist: certifi (==2023.5.7)
Requires-Dist: cffi (==1.15.1)
Requires-Dist: charset-normalizer (==3.1.0)
Requires-Dist: colorlog (==6.7.0)
Requires-Dist: croniter (==1.3.15)
Requires-Dist: crypto (==1.4.1)
Requires-Dist: cryptography (==41.0.1)
Requires-Dist: funcy (==2.0)
Requires-Dist: greenlet (==2.0.2)
Requires-Dist: idna (==3.4)
Requires-Dist: inflect (==6.0.4)
Requires-Dist: Naked (==0.1.32)
Requires-Dist: paramiko (==3.2.0)
Requires-Dist: pycparser (==2.21)
Requires-Dist: pycryptodome (==3.18.0)
Requires-Dist: pydantic (==1.10.8)
Requires-Dist: PyMySQL (==1.0.3)
Requires-Dist: PyNaCl (==1.5.0)
Requires-Dist: python-crontab (==2.7.1)
Requires-Dist: python-dateutil (==2.8.2)
Requires-Dist: PyYAML (==6.0)
Requires-Dist: requests (==2.31.0)
Requires-Dist: shellescape (==3.8.1)
Requires-Dist: six (==1.16.0)
Requires-Dist: sqlacodegen (==2.3.0.post1)
Requires-Dist: SQLAlchemy (==1.4.48)
Requires-Dist: typing-extensions (==4.6.2)
Requires-Dist: urllib3 (==2.0.2)
